camus.py
camus-1.0.0.dist-info/LICENSE
camus-1.0.0.dist-info/METADATA
camus-1.0.0.dist-info/WHEEL
camus-1.0.0.dist-info/top_level.txt
camus-1.0.0.dist-info/RECORD
