Metadata-Version: 2.1
Name: camus
Version: 1.0.0
Summary: A Records like database API that works with Aurora Serverless Data API
Home-page: https://github.com/risparfinance/camus
Author: Rafael Izidoro
Author-email: izidoro.rafa@gmail.com
License: MIT
Platform: UNKNOWN
Classifier: Development Status :: 3 - Alpha
Classifier: License :: OSI Approved :: MIT License
Classifier: Operating System :: OS Independent
Classifier: Programming Language :: Python :: 3
Classifier: Programming Language :: Python :: 3.5
Classifier: Programming Language :: Python :: 3.6
Classifier: Programming Language :: Python :: 3.7
Classifier: Programming Language :: Python :: 3.8
Classifier: Topic :: Utilities
Requires-Dist: boto3
